better_partial/__init__.py
better_partial/better_partial.py
better_partial/test.py
better_partial-1.0.6.dist-info/LICENSE
better_partial-1.0.6.dist-info/METADATA
better_partial-1.0.6.dist-info/WHEEL
better_partial-1.0.6.dist-info/top_level.txt
better_partial-1.0.6.dist-info/RECORD
